{
  "chainId": 42069,
  "deployedAt": "2026-04-05T02:40:00Z",
  "contracts": {
    "L2OutputOracle": {
      "address": "0x5FbDB2315678afecb367f032d93F642f64180aa3",
      "txHash": "deployed-via-forge-create"
    },
    "OptimismPortal": {
      "address": "0xe7f1725E7734CE288F8367e1Bb143E90bb3F0512",
      "txHash": "deployed-via-forge-create"
    },
    "SystemConfig": {
      "address": "0x9fE46736679d2D9a65F0992F2272dE9f3c7fa6e0",
      "txHash": "deployed-via-forge-create"
    },
    "L1StandardBridge": {
      "address": "0xCf7Ed3AccA5a467e9e704C703E8D87F634fB0Fc9",
      "txHash": "deployed-via-forge-create"
    }
  },
  "note": "Deployed to fresh L1 Anvil (chain 900, port 8546) alongside existing GoodDollar chain on 8545"
}
